request_ray/__init__.py
request_ray/rray.py
request_ray/test.py
request_ray-0.1.2.dist-info/LICENSE
request_ray-0.1.2.dist-info/METADATA
request_ray-0.1.2.dist-info/WHEEL
request_ray-0.1.2.dist-info/top_level.txt
request_ray-0.1.2.dist-info/RECORD
