Metadata-Version: 2.1
Name: request-ray
Version: 0.1.2
Summary: a batch based request package with retry stratgy that enables you to send X requests concurrently at rate of Y requests/execution
Home-page: https://github.com/Kareem-Emad/request-ray
Author: Kareem Emad
Author-email: kareememad400@gmail.com
License: MIT
Download-URL: https://pypi.org/project/request-ray/
Keywords: http,async,batch_execution,gevent
Platform: UNKNOWN
Requires-Dist: grequests (==0.6.0)
